eye2you/PandasDataset.py
eye2you/RetinaChecker.py
eye2you/RetinaCheckerPandas.py
eye2you/Service.py
eye2you/__init__.py
eye2you/checker.py
eye2you/datasets.py
eye2you/directnet.py
eye2you/factory.py
eye2you/helper_functions.py
eye2you/helper_functions.py.e68590312e1999009ef76568d87a5ad7.py
eye2you/image_helper.py
eye2you/inception_short.py
eye2you/io_helper.py
eye2you/make_default_config.py
eye2you/meter_functions.py
eye2you/model_wrapper.py
eye2you/models.py
eye2you/net.py
eye2you/services.py
eye2you/strip_checkpoint.py
eye2you/train.py
eye2you/transforms.py
eye2you/unet.py
eye2you-0.1.dev1.dist-info/LICENSE
eye2you-0.1.dev1.dist-info/METADATA
eye2you-0.1.dev1.dist-info/WHEEL
eye2you-0.1.dev1.dist-info/top_level.txt
eye2you-0.1.dev1.dist-info/RECORD
