Metadata-Version: 2.1
Name: eye2you
Version: 0.1.dev1
Summary: fundus image analysis
Home-page: https://github.com/phillies/eye2you
Author: Philipp Lies
Author-email: phil@lies.io
License: None
Platform: UNKNOWN
Classifier: Development Status :: 2 - Pre-Alpha
Classifier: Intended Audience :: Healthcare Industry
Classifier: Intended Audience :: Science/Research
Classifier: License :: Other/Proprietary License
Classifier: Topic :: Scientific/Engineering :: Artificial Intelligence
Classifier: Topic :: Scientific/Engineering :: Medical Science Apps.
Requires-Dist: pandas
Requires-Dist: torch
Requires-Dist: torchvision
Requires-Dist: opencv-python
Requires-Dist: sklearn
Requires-Dist: tqdm
Requires-Dist: pyyaml
Requires-Dist: imageio
